Lemon/__init__.py
Lemon/components.py
Lemon/conftest.py
Lemon/create_lemon_app.py
Lemon/Server/__init__.py
Lemon/Server/middleware.py
Lemon/Server/server.py
Lemon/orm/DBManager.py
Lemon/orm/__init__.py
Lemon/orm/migrations.py
Lemon/ui/__init__.py
Lemon/ui/buttons.py
Lemon/ui/forms.py
Lemon_Library-1.3.9.dist-info/LICENSE
Lemon_Library-1.3.9.dist-info/METADATA
Lemon_Library-1.3.9.dist-info/WHEEL
Lemon_Library-1.3.9.dist-info/entry_points.txt
Lemon_Library-1.3.9.dist-info/top_level.txt
Lemon_Library-1.3.9.dist-info/RECORD
