Metadata-Version: 2.1
Name: Lemon-Library
Version: 1.3.9
Summary: An experimental Full-Stack Framework for Python
Home-page: https://github.com/Sas2k/Lemon
Author: Sasen Perera
Author-email: sas8.communications@gmail.com
License: MIT License
Keywords: setuptools
Classifier: Development Status :: 5 - Production/Stable
Classifier: Intended Audience :: Developers
Classifier: License :: OSI Approved :: MIT License
Classifier: Operating System :: MacOS
Classifier: Operating System :: Microsoft :: Windows
Classifier: Operating System :: POSIX :: Linux
Classifier: Programming Language :: Python :: 3
Classifier: Programming Language :: Python :: 3.10
Classifier: Programming Language :: Python :: 3.9
License-File: LICENSE
Requires-Dist: parse
Requires-Dist: waitress
Requires-Dist: WebOB
Requires-Dist: whitenoise
Requires-Dist: requests
Requires-Dist: pytest
Requires-Dist: requests-wsgi-adapter
Requires-Dist: black
Requires-Dist: rich
